loadstar/__init__.py
loadstar/__main__.py
loadstar/analysis.py
loadstar/camera.py
loadstar/console.py
loadstar/cookstar.py
loadstar/fps.py
loadstar/util.py
loadstar/video.py
loadstar-1.1.dist-info/LICENSE
loadstar-1.1.dist-info/METADATA
loadstar-1.1.dist-info/WHEEL
loadstar-1.1.dist-info/entry_points.txt
loadstar-1.1.dist-info/top_level.txt
loadstar-1.1.dist-info/RECORD
