Metadata-Version: 2.1
Name: loadstar
Version: 1.1
Summary: Cooking Mama: Cookstar load removal tool.
Home-page: https://github.com/valknight/loadstar
Author: Vallerie Knight
Author-email: val@valknight.xyz
License: UNKNOWN
Project-URL: Bug Tracker, https://github.com/valknight/loadstar/issues
Platform: UNKNOWN
Classifier: Programming Language :: Python :: 3
Classifier: License :: OSI Approved :: MIT License
Classifier: Operating System :: OS Independent
Requires-Python: >=3.6
License-File: LICENSE
Requires-Dist: livesplit
Requires-Dist: opencv-python
Requires-Dist: click
